CHANGES.rst
MANIFEST.in
README.rst
setup.cfg
setup.py
docs/Makefile
docs/api.rst
docs/changelog.rst
docs/conf.py
docs/glossary.rst
docs/index.rst
docs/make.bat
docs/_build/doctrees/api.doctree
docs/_build/doctrees/changelog.doctree
docs/_build/doctrees/environment.pickle
docs/_build/doctrees/glossary.doctree
docs/_build/doctrees/index.doctree
docs/_build/doctrees/api/connection.doctree
docs/_build/doctrees/api/locking.doctree
docs/_build/doctrees/api/node.doctree
docs/_build/html/.buildinfo
docs/_build/html/api.html
docs/_build/html/changelog.html
docs/_build/html/genindex.html
docs/_build/html/glossary.html
docs/_build/html/index.html
docs/_build/html/objects.inv
docs/_build/html/py-modindex.html
docs/_build/html/search.html
docs/_build/html/searchindex.js
docs/_build/html/_modules/index.html
docs/_build/html/_modules/zktools/connection.html
docs/_build/html/_modules/zktools/locking.html
docs/_build/html/_modules/zktools/node.html
docs/_build/html/_sources/api.txt
docs/_build/html/_sources/changelog.txt
docs/_build/html/_sources/glossary.txt
docs/_build/html/_sources/index.txt
docs/_build/html/_sources/api/connection.txt
docs/_build/html/_sources/api/locking.txt
docs/_build/html/_sources/api/node.txt
docs/_build/html/_static/ajax-loader.gif
docs/_build/html/_static/basic.css
docs/_build/html/_static/comment-bright.png
docs/_build/html/_static/comment-close.png
docs/_build/html/_static/comment.png
docs/_build/html/_static/default.css
docs/_build/html/_static/doctools.js
docs/_build/html/_static/down-pressed.png
docs/_build/html/_static/down.png
docs/_build/html/_static/file.png
docs/_build/html/_static/jquery.js
docs/_build/html/_static/minus.png
docs/_build/html/_static/plus.png
docs/_build/html/_static/pygments.css
docs/_build/html/_static/searchtools.js
docs/_build/html/_static/sidebar.js
docs/_build/html/_static/underscore.js
docs/_build/html/_static/up-pressed.png
docs/_build/html/_static/up.png
docs/_build/html/_static/websupport.js
zktools.egg-info/PKG-INFO
zktools.egg-info/SOURCES.txt
zktools.egg-info/dependency_links.txt
zktools.egg-info/entry_points.txt
zktools.egg-info/not-zip-safe
zktools.egg-info/requires.txt
zktools.egg-info/top_level.txt
