Metadata-Version: 1.0
Name: zktools
Version: 0.2.1
Summary: Zookeeper Tools
Home-page: http://zktools.readthedocs.org/
Author: Mozilla Foundation
Author-email: bbangert@mozilla.com
License: MPLv2.0
Keywords: zookeeper lock leader configuration
Platform: UNKNOWN
Classifier: Intended Audience :: Developers
Classifier: Programming Language :: Python
Classifier: License :: OSI Approved :: Mozilla Public License 2.0 (MPL 2.0)
